Metadata-Version: 2.4
Name: cubist
Version: 1.2.1
Summary: A Python package for fitting Ross Quinlan's Cubist regression model.
Author: Ross Quinlan, Max Kuhn, Patrick Aselin
Maintainer: Patrick Aselin
License-Expression: GPL-3.0
Project-URL: Homepage, https://github.com/pjaselin/Cubist
Project-URL: Repository, https://github.com/pjaselin/Cubist.git
Project-URL: Issues, https://github.com/pjaselin/Cubist/issues
Classifier: Development Status :: 5 - Production/Stable
Classifier: Intended Audience :: Developers
Classifier: Intended Audience :: Science/Research
Classifier: Topic :: Software Development :: Libraries
Classifier: Topic :: Scientific/Engineering :: Artificial Intelligence
Classifier: Topic :: Scientific/Engineering :: Mathematics
Classifier: Programming Language :: Python :: 3.10
Classifier: Programming Language :: Python :: 3.11
Classifier: Programming Language :: Python :: 3.12
Classifier: Programming Language :: Python :: 3.13
Classifier: Programming Language :: Python :: 3.14
Requires-Python: >=3.10
License-File: LICENSE
Requires-Dist: numpy
Requires-Dist: pandas>=2.2.2
Requires-Dist: scikit-learn>=1.6.0
Provides-Extra: viz
Requires-Dist: matplotlib; extra == "viz"
Dynamic: license-file
